<?xml version="1.1" encoding="UTF-8"?>

<!--
 * See the NOTICE file distributed with this work for additional
 * information regarding copyright ownership.
 *
 * This is free software; you can redistribute it and/or modify it
 * under the terms of the GNU Lesser General Public License as
 * published by the Free Software Foundation; either version 2.1 of
 * the License, or (at your option) any later version.
 *
 * This software is distributed in the hope that it will be useful,
 * but WITHOUT ANY WARRANTY; without even the implied warranty of
 * MERCHANTABILITY or FITNESS FOR A PARTICULAR PURPOSE. See the GNU
 * Lesser General Public License for more details.
 *
 * You should have received a copy of the GNU Lesser General Public
 * License along with this software; if not, write to the Free
 * Software Foundation, Inc., 51 Franklin St, Fifth Floor, Boston, MA
 * 02110-1301 USA, or see the FSF site: http://www.fsf.org.
-->

<xwikidoc version="1.5" reference="AzureADAdmin.Translations" locale="">
  <web>AzureADAdmin</web>
  <name>Translations</name>
  <language/>
  <defaultLanguage>en</defaultLanguage>
  <translation>0</translation>
  <creator>xwiki:XWiki.Admin</creator>
  <parent>AzureADAdmin.WebHome</parent>
  <author>xwiki:XWiki.Admin</author>
  <contentAuthor>xwiki:XWiki.Admin</contentAuthor>
  <version>1.1</version>
  <title/>
  <comment/>
  <minorEdit>false</minorEdit>
  <syntaxId>plain/1.0</syntaxId>
  <hidden>true</hidden>
  <content>admin.azureAD=Azure AD
# Login page
azureADAdmin.loginWithAzureAD = Login with Azure Active Directory

# Admin (extras compared to IdentityOAuth/Translations
azureADAdmin.config.heading=AzureAD Integration Configuration
azureADAdmin.AzureADConfigClass_config.explanation=XWiki can be integrated to login XWiki users with Azure Active Directory
azureAD.extension.name=Microsoft Azure Active Directory Single Sign-On (SSO) (Pro)

azureADAdmin.AzureADConfigClass_communicate=Communication with the Azure Active Directory services
azureADAdmin.AzureADConfigClass_communicate.hint=To activate the Azure AD integration you need to {0} and to insert your client-Id, tenant-id and secret in the following settings.
azureADAdmin.AzureADConfigClass_communicate.hint.linkLabel=register for OAuth access on the Microsoft Azure console
azureADAdmin.AzureADConfigClass_communicate.hint2=For more information, please see {0}.
azureADAdmin.AzureADConfigClass_communicate.hint2.linkLabel=the installation instructions

azureADAdmin.AzureADConfigClass_tenantid=Tenant ID
azureADAdmin.AzureADConfigClass_tenantid.hint=As provided in the Azure overview.


azureADAdmin.AzureADConfigClass_nowWhat1=Once this is configured please log out and login by clicking "Login with Azure AD".
azureADAdmin.AzureADConfigClass_nowWhat2=Should you have technical difficulties, please write to support@xwikisas.com .

## a single change for avatar's setting
azureADAdmin.AzureADConfigClass_scope_avatar.onlyOutlook = only works with Outlook-enabled-accounts, a {0} limitation
azureADAdmin.AzureADConfigClass_scope_avatar.onlyOutlook.linkLabel=known</content>
  <object>
    <name>AzureADAdmin.Translations</name>
    <number>0</number>
    <className>XWiki.TranslationDocumentClass</className>
    <guid>01d84622-baf7-448b-96a4-93fcd4276764</guid>
    <class>
      <name>XWiki.TranslationDocumentClass</name>
      <customClass/>
      <customMapping/>
      <defaultViewSheet/>
      <defaultEditSheet/>
      <defaultWeb/>
      <nameField/>
      <validationScript/>
      <scope>
        <cache>0</cache>
        <disabled>0</disabled>
        <displayType>select</displayType>
        <freeText>forbidden</freeText>
        <largeStorage>0</largeStorage>
        <multiSelect>0</multiSelect>
        <name>scope</name>
        <number>1</number>
        <prettyName>Scope</prettyName>
        <relationalStorage>0</relationalStorage>
        <separator> </separator>
        <separators>|, </separators>
        <size>1</size>
        <unmodifiable>0</unmodifiable>
        <values>GLOBAL|WIKI|USER|ON_DEMAND</values>
        <classType>com.xpn.xwiki.objects.classes.StaticListClass</classType>
      </scope>
    </class>
    <property>
      <scope>WIKI</scope>
    </property>
  </object>
</xwikidoc>
